Metadata-Version: 1.0
Name: sta-distributions11
Version: 0.1
Summary: Gaussian distributions
Home-page: UNKNOWN
Author: Chidume Jacob
Author-email: chidumejacob@gmail.com
License: UNKNOWN
Platform: UNKNOWN
